.travis.yml
LICENSE.txt
MANIFEST.in
README.rst
pyproject.toml
setup.cfg
setup.py
tox.ini
benchmarks/grep.py
src/constants.h
src/constants.pxd
src/fmmap.c
src/fmmap.pyx
src/fmmap.egg-info/PKG-INFO
src/fmmap.egg-info/SOURCES.txt
src/fmmap.egg-info/dependency_links.txt
src/fmmap.egg-info/requires.txt
src/fmmap.egg-info/top_level.txt
tests/__init__.py
tests/test_extra.py
tests/test_mmap.py
tests/test_mmap_pypy.py