Metadata-Version: 2.1
Name: fmmap
Version: 2.0.0
Summary: A fast reimplementation of mmap
Home-page: https://github.com/friedelwolff/fmmap/
Author: Friedel Wolff
Author-email: friedel@translate.org.za
License: UNKNOWN
Project-URL: Bug Reports, https://github.com/friedelwolff/fmmap/issues
Project-URL: Source, https://github.com/friedelwolff/fmmap/
Keywords: mmap
Platform: UNKNOWN
Classifier: Development Status :: 5 - Production/Stable
Classifier: Intended Audience :: Developers
Classifier: License :: OSI Approved :: Mozilla Public License 2.0 (MPL 2.0)
Classifier: Programming Language :: Cython
Classifier: Programming Language :: Python :: 3.4
Classifier: Programming Language :: Python :: 3.5
Classifier: Programming Language :: Python :: 3.6
Classifier: Programming Language :: Python :: 3.7
Classifier: Programming Language :: Python :: 3.8
Classifier: Programming Language :: Python :: 3.9
Classifier: Operating System :: POSIX :: Linux
Classifier: Operating System :: POSIX :: BSD :: FreeBSD
Classifier: Operating System :: POSIX :: BSD :: NetBSD
Classifier: Operating System :: POSIX :: BSD :: OpenBSD
Classifier: Operating System :: POSIX :: SunOS/Solaris
Classifier: Operating System :: MacOS :: MacOS X
Classifier: Operating System :: Microsoft :: Windows
Requires-Python: >=3.4, <4
Provides-Extra: test
Provides-Extra: dev
